README.md
setup.py
su_audio_utils/__init__.py
su_audio_utils/audio_util.py
su_audio_utils/audio_wav.py
su_audio_utils.egg-info/PKG-INFO
su_audio_utils.egg-info/SOURCES.txt
su_audio_utils.egg-info/dependency_links.txt
su_audio_utils.egg-info/not-zip-safe
su_audio_utils.egg-info/top_level.txt
test/test.py