Metadata-Version: 2.1
Name: su-audio-utils
Version: 0.0.1
Summary: Personal audio utils.
Home-page: https://github.com/SuCicada/su-audio-utils
Author: SuCicada
Author-email: pengyifu@gmail.com
Classifier: Programming Language :: Python :: 3
Classifier: License :: OSI Approved :: MIT License
Classifier: Operating System :: OS Independent
